odoo9_addon_l10n_ec-9.0.1.0.0-py2.7-nspkg.pth
odoo_addons/l10n_ec/__openerp__.py
odoo_addons/l10n_ec/__init__.py
odoo_addons/l10n_ec/README.rst
odoo_addons/l10n_ec/data/account_chart_template.yml
odoo_addons/l10n_ec/data/account.account.template.csv
odoo_addons/l10n_ec/data/account_chart_template.xml
odoo_addons/l10n_ec/static/description/icon.png
odoo9_addon_l10n_ec-9.0.1.0.0.dist-info/top_level.txt
odoo9_addon_l10n_ec-9.0.1.0.0.dist-info/WHEEL
odoo9_addon_l10n_ec-9.0.1.0.0.dist-info/RECORD
odoo9_addon_l10n_ec-9.0.1.0.0.dist-info/metadata.json
odoo9_addon_l10n_ec-9.0.1.0.0.dist-info/DESCRIPTION.rst
odoo9_addon_l10n_ec-9.0.1.0.0.dist-info/METADATA
odoo9_addon_l10n_ec-9.0.1.0.0.dist-info/namespace_packages.txt
